{
    "version": "0.33.1",
    "architecture": {
        "64bit": {
            "url": "https://github.com/AlexBurnes/buildfab/releases/download/v0.33.1/buildfab_windows_amd64.zip",
            "bin": [
                "buildfab.exe"
            ],
            "hash": "1f9c117f78ed0c483dc8f3118cbdd7c4f100225c7d6d43dcd52c1dcef05e3512"
        },
        "arm64": {
            "url": "https://github.com/AlexBurnes/buildfab/releases/download/v0.33.1/buildfab_windows_arm64.zip",
            "bin": [
                "buildfab.exe"
            ],
            "hash": "b793fc25d8a61db72ff6adcc10ba51fab2dcfa50853ea67414ab3590aa75dc60"
        }
    },
    "homepage": "https://github.com/AlexBurnes/buildfab",
    "license": "MIT",
    "description": "Go-based automation runner with DAG executor"
}