{
    "version": "0.25.0",
    "architecture": {
        "64bit": {
            "url": "https://github.com/AlexBurnes/buildfab/releases/download/v0.25.0/buildfab_windows_amd64.zip",
            "bin": [
                "buildfab.exe"
            ],
            "hash": "0f2e2475869832b7a9d15e43d0b53cf61da4c3e28eb9f1ee2ba3fb8a6abfb583"
        },
        "arm64": {
            "url": "https://github.com/AlexBurnes/buildfab/releases/download/v0.25.0/buildfab_windows_arm64.zip",
            "bin": [
                "buildfab.exe"
            ],
            "hash": "f25da96e6bf9e22a94a66ac401faaee17e5d18fda3af5aac8668ecf1f17c540a"
        }
    },
    "homepage": "https://github.com/AlexBurnes/buildfab",
    "license": "MIT",
    "description": "Go-based automation runner with DAG executor"
}