{
    "version": "0.10.0",
    "architecture": {
        "64bit": {
            "url": "https://github.com/AlexBurnes/buildfab/releases/download/v0.10.0/buildfab_windows_amd64.zip",
            "bin": [
                "buildfab.exe"
            ],
            "hash": "a44b64ee54cfe0e1a6bcd9d3fcb25bb4e57fc6a3440b7845465e58571f075e80"
        },
        "arm64": {
            "url": "https://github.com/AlexBurnes/buildfab/releases/download/v0.10.0/buildfab_windows_arm64.zip",
            "bin": [
                "buildfab.exe"
            ],
            "hash": "2051886dcb0bb98df1a6a8579f2a9453884e223016454d5e6c8ef5d1b7c983cc"
        }
    },
    "homepage": "https://github.com/AlexBurnes/buildfab",
    "license": "MIT",
    "description": "Go-based automation runner with DAG executor"
}