{
    "version": "1.6.3",
    "architecture": {
        "64bit": {
            "url": "https://github.com/AlexBurnes/pre-push/releases/download/v1.6.3/pre-push_windows_amd64.zip",
            "bin": [
                "pre-push.exe"
            ],
            "hash": "2468755264ff86f4699f2876cfdc2f207724bbbf62cd354522ac4d5bd3ef6528"
        },
        "arm64": {
            "url": "https://github.com/AlexBurnes/pre-push/releases/download/v1.6.3/pre-push_windows_arm64.zip",
            "bin": [
                "pre-push.exe"
            ],
            "hash": "0fc74eccc66c7fe2d5f2fe1e5c7646491fbe64dc7cc6abbd25413868a23347ac"
        }
    },
    "homepage": "https://github.com/AlexBurnes/pre-push",
    "license": "Apache-2.0",
    "description": "Cross-platform Git pre-push hook runner"
}