{
    "version": "1.1.1",
    "architecture": {
        "64bit": {
            "url": "https://github.com/AlexBurnes/version-go/releases/download/v1.1.1/version_windows_amd64.zip",
            "bin": [
                "version.exe"
            ],
            "hash": "9b2221ca67b0183f1731feebbe8b233c417e2e16757c95ccb1f2915631951be9"
        },
        "arm64": {
            "url": "https://github.com/AlexBurnes/version-go/releases/download/v1.1.1/version_windows_arm64.zip",
            "bin": [
                "version.exe"
            ],
            "hash": "9dce28eea4ff27556d1a28033ee35e62fcaa1f60fb5a4ff82f1baae3bf70c948"
        }
    },
    "homepage": "https://github.com/AlexBurnes/version-go",
    "license": "MIT",
    "description": "git describe-like CLI"
}